<?xml version="1.0" encoding="utf-8" ?>
<dwsync>
<file name="animate.js" server="beta.teamexon.eu//web/qeditor/" local="130399760928133947" remote="130399762200000000" Dst="1" />
<file name="custom.js" server="beta.teamexon.eu//web/qeditor/" local="130401507121447542" remote="130401507600000000" Dst="1" />
<file name="inview.js" server="beta.teamexon.eu//web/qeditor/" local="130399760828534289" remote="130399762200000000" Dst="1" />
<file name="bootstrap.js" server="beta.teamexon.eu//web/qeditor/" local="130399760326358633" remote="130399762200000000" Dst="1" />
<file name="isotope.js" server="beta.teamexon.eu//web/qeditor/" local="130399760567437726" remote="130399762200000000" Dst="1" />
<file name="jquery.flexslider.js" server="beta.teamexon.eu//web/qeditor/" local="130399760704176200" remote="130399762200000000" Dst="1" />
<file name="jquery.localscroll-1.2.7-min.js" server="beta.teamexon.eu//web/qeditor/" local="130399760197533875" remote="130399762200000000" Dst="1" />
<file name="jquery.js" server="beta.teamexon.eu//web/qeditor/" local="130400710996054294" remote="130400711400000000" Dst="1" />
<file name="jquery.nav.js" server="beta.teamexon.eu//web/qeditor/" local="130399759972297455" remote="130399762200000000" Dst="1" />
<file name="jquery.scrollTo.js" server="beta.teamexon.eu//web/qeditor/" local="130399759814107016" remote="130399762200000000" Dst="1" />
<file name="jquery.tweet.js" server="beta.teamexon.eu//web/qeditor/" local="130401200675429644" remote="130401201000000000" Dst="1" />
<file name="validate.js" server="beta.teamexon.eu//web/qeditor/" local="130402487577550499" remote="130402487400000000" Dst="1" />
<file name="jquery.prettyPhoto.js" server="beta.teamexon.eu//web/qeditor/" local="130400612273230002" remote="130400614200000000" Dst="1" />
<file name="bootstrap-image-gallery.min.js" server="beta.teamexon.eu//web/qeditor/" local="130286873380000000" remote="130400731200000000" Dst="1" />
<file name="lightbox-2.6.min.js" server="beta.teamexon.eu//web/qeditor/" local="130400737362708898" remote="130400739000000000" Dst="1" />
<file name="index.php" server="beta.teamexon.eu//web/qeditor/" local="130401682380567266" remote="130401682800000000" Dst="1" />
<file name="jquery.fancybox.js" server="beta.teamexon.eu//web/qeditor/" local="130156459480000000" remote="130401301200000000" Dst="1" />
<file name="jquery.fancybox.pack.js" server="beta.teamexon.eu//web/qeditor/" local="130156459480000000" remote="130401301200000000" Dst="1" />
<file name="jquery.fancybox-buttons.js" server="beta.teamexon.eu//web/qeditor/" local="130156459480000000" remote="130401504000000000" Dst="1" />
<file name="jquery.fancybox-media.js" server="beta.teamexon.eu//web/qeditor/" local="130156459480000000" remote="130401504000000000" Dst="1" />
<file name="jquery.fancybox-thumbs.js" server="beta.teamexon.eu//web/qeditor/" local="130156459480000000" remote="130401504000000000" Dst="1" />
<file name="animate.js" server="beta.teamexon.eu//web/" local="130399760928133947" remote="130405968000000000" Dst="1" />
<file name="bootstrap-image-gallery.min.js" server="beta.teamexon.eu//web/" local="130286873380000000" remote="130405968000000000" Dst="1" />
<file name="custom.js" server="beta.teamexon.eu//web/" local="130405964933150918" remote="130405968000000000" Dst="1" />
<file name="bootstrap.js" server="beta.teamexon.eu//web/" local="130399760326358633" remote="130405968000000000" Dst="1" />
<file name="index.php" server="beta.teamexon.eu//web/" local="130401682380567266" remote="130405968000000000" Dst="1" />
<file name="inview.js" server="beta.teamexon.eu//web/" local="130399760828534289" remote="130405968000000000" Dst="1" />
<file name="isotope.js" server="beta.teamexon.eu//web/" local="130399760567437726" remote="130405968000000000" Dst="1" />
<file name="jquery.fancybox-buttons.js" server="beta.teamexon.eu//web/" local="130156459480000000" remote="130405968000000000" Dst="1" />
<file name="jquery.fancybox-media.js" server="beta.teamexon.eu//web/" local="130156459480000000" remote="130405968000000000" Dst="1" />
<file name="jquery.fancybox-thumbs.js" server="beta.teamexon.eu//web/" local="130156459480000000" remote="130405968000000000" Dst="1" />
<file name="jquery.fancybox.js" server="beta.teamexon.eu//web/" local="130156459480000000" remote="130405968000000000" Dst="1" />
<file name="jquery.fancybox.pack.js" server="beta.teamexon.eu//web/" local="130156459480000000" remote="130405968000000000" Dst="1" />
<file name="jquery.flexslider.js" server="beta.teamexon.eu//web/" local="130399760704176200" remote="130405968000000000" Dst="1" />
<file name="jquery.localscroll-1.2.7-min.js" server="beta.teamexon.eu//web/" local="130399760197533875" remote="130405968000000000" Dst="1" />
<file name="jquery.js" server="beta.teamexon.eu//web/" local="130400710996054294" remote="130405968000000000" Dst="1" />
<file name="jquery.nav.js" server="beta.teamexon.eu//web/" local="130399759972297455" remote="130405968000000000" Dst="1" />
<file name="jquery.scrollTo.js" server="beta.teamexon.eu//web/" local="130399759814107016" remote="130405968000000000" Dst="1" />
<file name="jquery.prettyPhoto.js" server="beta.teamexon.eu//web/" local="130400612273230002" remote="130405968000000000" Dst="1" />
<file name="jquery.tweet.js" server="beta.teamexon.eu//web/" local="130401200675429644" remote="130405968000000000" Dst="1" />
<file name="lightbox-2.6.min.js" server="beta.teamexon.eu//web/" local="130400737362708898" remote="130405968000000000" Dst="1" />
<file name="validate.js" server="beta.teamexon.eu//web/" local="130402487577550499" remote="130405968000000000" Dst="1" />
</dwsync>